py_sas_studio_custom_steps/__init__.py
py_sas_studio_custom_steps/custom_step.py
py_sas_studio_custom_steps-0.5.1.dist-info/LICENSE
py_sas_studio_custom_steps-0.5.1.dist-info/METADATA
py_sas_studio_custom_steps-0.5.1.dist-info/WHEEL
py_sas_studio_custom_steps-0.5.1.dist-info/top_level.txt
py_sas_studio_custom_steps-0.5.1.dist-info/RECORD
