Metadata-Version: 2.2
Name: py_sas_studio_custom_steps
Version: 0.5.1
Summary: A package containing a Python class and associated methods to facilitate operations on SAS Studio Custom Steps.
Author-email: Sundaresh Sankaran <sundaresh.sankaran@sas.com>
Project-URL: Homepage, https://github.com/SundareshSankaran/py-sas-studio-custom-steps
Project-URL: Issues, https://github.com/SundareshSankaran/py-sas-studio-custom-steps/issues
Classifier: Programming Language :: Python :: 3
Classifier: License :: OSI Approved :: Apache Software License
Classifier: Operating System :: OS Independent
Requires-Python: >=3.10
License-File: LICENSE
